jupyterlab_sql_plugin/__init__.py
jupyterlab_sql_plugin/_version.py
jupyterlab_sql_plugin/cache.py
jupyterlab_sql_plugin/connection_url.py
jupyterlab_sql_plugin/executor.py
jupyterlab_sql_plugin/handlers.py
jupyterlab_sql_plugin/models.py
jupyterlab_sql_plugin/request_decoder.py
jupyterlab_sql_plugin/responses.py
jupyterlab_sql_plugin/schema_loader.py
jupyterlab_sql_plugin/serializer.py
jupyterlab_sql_plugin/version.py
jupyterlab_sql_plugin/labextension/build_log.json
jupyterlab_sql_plugin/labextension/package.json
jupyterlab_sql_plugin/labextension/schemas/jupyterlab-sql-plugin/package.json.orig
jupyterlab_sql_plugin/labextension/schemas/jupyterlab-sql-plugin/plugin.json
jupyterlab_sql_plugin/labextension/static/lib_index_js.af2355d778bcdf9c10c9.js
jupyterlab_sql_plugin/labextension/static/lib_index_js.af2355d778bcdf9c10c9.js.map
jupyterlab_sql_plugin/labextension/static/remoteEntry.771ff9fc6a526433b309.js
jupyterlab_sql_plugin/labextension/static/remoteEntry.771ff9fc6a526433b309.js.map
jupyterlab_sql_plugin/labextension/static/style.js
jupyterlab_sql_plugin/labextension/static/style_index_js.3277283731e17752db4e.js
jupyterlab_sql_plugin/labextension/static/style_index_js.3277283731e17752db4e.js.map
jupyterlab_sql_plugin/labextension/static/vendors-node_modules_classnames_index_js-node_modules_css-loader_dist_runtime_getUrl_js-node_-91c075.1b7f0ab3835c29fab2ff.js
jupyterlab_sql_plugin/labextension/static/vendors-node_modules_classnames_index_js-node_modules_css-loader_dist_runtime_getUrl_js-node_-91c075.1b7f0ab3835c29fab2ff.js.map
jupyterlab_sql_plugin/labextension/static/vendors-node_modules_css-loader_dist_runtime_api_js-node_modules_css-loader_dist_runtime_cssW-72eba1.b9e27b4d373e9ca6dd02.js
jupyterlab_sql_plugin/labextension/static/vendors-node_modules_css-loader_dist_runtime_api_js-node_modules_css-loader_dist_runtime_cssW-72eba1.b9e27b4d373e9ca6dd02.js.map
jupyterlab_sql_plugin-0.1.0.dist-info/LICENSE
jupyterlab_sql_plugin-0.1.0.dist-info/METADATA
jupyterlab_sql_plugin-0.1.0.dist-info/WHEEL
jupyterlab_sql_plugin-0.1.0.dist-info/top_level.txt
jupyterlab_sql_plugin-0.1.0.dist-info/RECORD
